ganrectf/__init__.py
ganrectf/_version.py
ganrectf/config.json
ganrectf/ganrec.py
ganrectf/models.py
ganrectf/propagators.py
ganrectf/tfutils.py
ganrectf/utils.py
ganrectorch/__init__.py
ganrectorch/_version.py
ganrectorch/config.json
ganrectorch/ganrec.py
ganrectorch/models.py
ganrectorch/propagators.py
ganrectorch/utils.py
ganrec-0.3.0.dist-info/METADATA
ganrec-0.3.0.dist-info/WHEEL
ganrec-0.3.0.dist-info/licenses/AUTHORS.rst
ganrec-0.3.0.dist-info/licenses/LICENSE
ganrec-0.3.0.dist-info/RECORD
