Metadata-Version: 2.4
Name: ganrec
Version: 0.3.0
Summary: A deep neural network data reconstruction platform
Project-URL: homepage, https://github.com/XYangXRay/ganrec
Project-URL: repository, https://github.com/XYangXRay/ganrec
Project-URL: documentation, https://github.com/XYangXRay/ganrec
Author-email: Xiaogang Yang <xiaogang.yang@outlook.com>
License: BSD 3-Clause License
License-File: AUTHORS.rst
License-File: LICENSE
Keywords: Data reconstruction,GAN,Phase retrieval,Tomography
Classifier: License :: OSI Approved :: MIT License
Classifier: Operating System :: OS Independent
Classifier: Programming Language :: Python :: 3
Requires-Python: >=3.9
Requires-Dist: ipykernel>=6.0.0
Requires-Dist: ipython>=8.12.3
Requires-Dist: matplotlib>=3.3.2
Requires-Dist: numpy>=1.19.2
Requires-Dist: scikit-image>=0.19.3
Requires-Dist: tifffile>=2023.12.9
Requires-Dist: tqdm>=4.65.0
Provides-Extra: pytorch
Requires-Dist: quantities; extra == 'pytorch'
Requires-Dist: torch>=2.0.0; extra == 'pytorch'
Requires-Dist: torchvision; extra == 'pytorch'
Provides-Extra: tensorflow
Requires-Dist: tensorflow[and-cuda]>=2.17.0; extra == 'tensorflow'
